{
    "model": {
        "type": "minecraft:condition",
        "on_false": {
            "type":"minecraft:range_dispatch",
            "property": "minecraft:damage",
            "fallback": {
                "type": "minecraft:model",
                "model": "minecraft:item/bow"
            },
            "entries":[
                {
                    "threshold": 0.9,
                    "model": {
                        "type": "minecraft:model",
                        "model": "minecraft:item/bow/warning"            
                    }
                },
                {
                    "threshold": 0.99,
                    "model": {
                        "type": "minecraft:model",
                        "model": "minecraft:item/bow/critical"            
                    }
                }
            ]
        },
        "on_true": {
            "type": "minecraft:range_dispatch",
            "entries": [
                {
                    "model": {
                        "type": "minecraft:range_dispatch",
                        "property":"minecraft:damage",
                        "fallback": {
                            "type": "minecraft:model",
                            "model": "minecraft:item/bow_pulling_1"    
                        },
                        "entries": [
                            {
                                "threshold": 0.9,
                                "model": {
                                    "type":"minecraft:model",
                                    "model":"minecraft:item/bow_pulling_1/warning"
                                }
                            },
                            {
                                "threshold": 0.99,
                                "model": {
                                    "type":"minecraft:model",
                                    "model":"minecraft:item/bow_pulling_1/critical"
                                }
                            }
                        ]
                    },
                    "threshold": 0.65
                },
                {
                    "model": {
                        "type":"minecraft:range_dispatch",
                        "property":"minecraft:damage",
                        "fallback":{
                            "type": "minecraft:model",
                            "model": "minecraft:item/bow_pulling_2"    
                        },
                        "entries":[
                            {
                                "threshold": 0.9,
                                "model": {
                                    "type": "minecraft:model",
                                    "model": "minecraft:item/bow_pulling_2/warning"            
                                }
                            },
                            {
                                "threshold": 0.99,
                                "model": {
                                    "type": "minecraft:model",
                                    "model": "minecraft:item/bow_pulling_2/critical"            
                                }
                            }
                        ]
                    },
                    "threshold": 0.9
                }
            ],
            "fallback": {
                "type": "minecraft:range_dispatch",
                "property": "minecraft:damage",
                "fallback": {
                    "type": "minecraft:model",
                    "model": "minecraft:item/bow_pulling_0"    
                },
                "entries": [
                    {
                        "threshold": 0.9,
                        "model": {
                            "type": "minecraft:model",
                            "model": "minecraft:item/bow_pulling_0/warning"
                        }
                    },
                    {
                        "threshold": 0.99,
                        "model": {
                            "type": "minecraft:model",
                            "model": "minecraft:item/bow_pulling_0/critical"
                        }
                    }
                ]
            },
            "property": "minecraft:use_duration",
            "scale": 0.05
        },
        "property": "minecraft:using_item"
    }
}